s3_mcp/__init__.py
s3_mcp/__main__.py
s3_mcp/server.py
s3_mcp/s3/__init__.py
s3_mcp/s3/client.py
s3_mcp/s3/operations.py
s3_mcp/s3/utils.py
s3_mcp-0.1.0.dist-info/METADATA
s3_mcp-0.1.0.dist-info/WHEEL
s3_mcp-0.1.0.dist-info/entry_points.txt
s3_mcp-0.1.0.dist-info/RECORD
