Metadata-Version: 2.4
Name: s3-mcp
Version: 0.1.0
Summary: MCP Server for AWS S3 operations with presigned URL support
Author-email: Synteles <info@synteles.com>
Keywords: aws,mcp,model-context-protocol,presigned-url,s3,server
Classifier: Development Status :: 4 - Beta
Classifier: Intended Audience :: Developers
Classifier: Programming Language :: Python :: 3
Classifier: Programming Language :: Python :: 3.10
Classifier: Programming Language :: Python :: 3.11
Classifier: Programming Language :: Python :: 3.12
Classifier: Programming Language :: Python :: 3.13
Requires-Python: >=3.10
Requires-Dist: boto3>=1.34.0
Requires-Dist: fastmcp>=0.2.0
Requires-Dist: pydantic>=2.0.0
Requires-Dist: python-dotenv>=1.0.0
Provides-Extra: dev
Requires-Dist: boto3-stubs[s3]>=1.34.0; extra == 'dev'
Requires-Dist: moto[s3]>=4.0.0; extra == 'dev'
Requires-Dist: mypy>=1.0.0; extra == 'dev'
Requires-Dist: pytest-asyncio>=0.21.0; extra == 'dev'
Requires-Dist: pytest-cov>=4.0.0; extra == 'dev'
Requires-Dist: pytest>=7.0.0; extra == 'dev'
Requires-Dist: ruff>=0.1.0; extra == 'dev'
